Metadata-Version: 2.1
Name: WatchPython
Version: 0.1.3
Summary: A re-implementation of the Unix watch command in Python.
Home-page: https://github.com/asweigart/watchpython
Author: Al Sweigart
Author-email: al@inventwithpython.com
License: MIT
Keywords: watch
Platform: UNKNOWN
Classifier: License :: OSI Approved :: MIT License
Classifier: Programming Language :: Python
Classifier: Programming Language :: Python :: 3
Classifier: Programming Language :: Python :: 3.5
Classifier: Programming Language :: Python :: 3.6
Classifier: Programming Language :: Python :: 3.7
Classifier: Programming Language :: Python :: 3.8
Classifier: Programming Language :: Python :: 3.9
